humbug/__init__.py
humbug/blacklist.py
humbug/consent.py
humbug/py.typed
humbug/report.py
humbug/system_information.py
humbug/test_blacklist.py
humbug/test_consent.py
humbug/test_report.py
humbug/test_system_information.py
humbug/utils.py
humbug-0.3.2.dist-info/METADATA
humbug-0.3.2.dist-info/WHEEL
humbug-0.3.2.dist-info/top_level.txt
humbug-0.3.2.dist-info/RECORD
