Metadata-Version: 2.1
Name: humbug
Version: 0.3.2
Summary: Humbug: Do you build developer tools? Humbug helps you know your users.
Home-page: https://github.com/bugout-dev/humbug
Author: Bugout.dev
Author-email: engineering@bugout.dev
License: UNKNOWN
Platform: UNKNOWN
Classifier: Development Status :: 3 - Alpha
Classifier: Programming Language :: Python
Classifier: License :: OSI Approved :: Apache Software License
Classifier: Topic :: Software Development :: Libraries
Provides-Extra: dev
Provides-Extra: distribute
Provides-Extra: profile
